LICENSE
MANIFEST.in
README.md
setup.py
./builelib/climatedata/117.csv
./builelib/climatedata/124.csv
./builelib/climatedata/186.csv
./builelib/climatedata/190.csv
./builelib/climatedata/230.csv
./builelib/climatedata/286.csv
./builelib/climatedata/292.csv
./builelib/climatedata/401.csv
./builelib/climatedata/403.csv
./builelib/climatedata/412.csv
./builelib/climatedata/420.csv
./builelib/climatedata/423.csv
./builelib/climatedata/426.csv
./builelib/climatedata/438.csv
./builelib/climatedata/473.csv
./builelib/climatedata/480.csv
./builelib/climatedata/49.csv
./builelib/climatedata/495.csv
./builelib/climatedata/542.csv
./builelib/climatedata/551.csv
./builelib/climatedata/569.csv
./builelib/climatedata/59-A4.csv
./builelib/climatedata/59-A5.csv
./builelib/climatedata/59.csv
./builelib/climatedata/593.csv
./builelib/climatedata/63.csv
./builelib/climatedata/7.csv
./builelib/climatedata/797.csv
./builelib/climatedata/798.csv
./builelib/climatedata/819-A1.csv
./builelib/climatedata/819-A2.csv
./builelib/climatedata/819.csv
./builelib/climatedata/826.csv
./builelib/climatedata/836.csv
./builelib/climatedata/842.csv
./builelib/climatedata/C1_0598195.has
./builelib/climatedata/C1_0868195.has
./builelib/climatedata/C1_2248195.has
./builelib/climatedata/C1_3338195.has
./builelib/climatedata/C1_3938195.has
./builelib/climatedata/C1_6158195.has
./builelib/climatedata/C1_7948195.has
./builelib/climatedata/C1_8318195.has
./builelib/climatedata/weath_II.dat
./builelib/climatedata/weath_III.dat
./builelib/climatedata/weath_IVa.dat
./builelib/climatedata/weath_IVb.dat
./builelib/climatedata/weath_Ia.dat
./builelib/climatedata/weath_Ib.dat
./builelib/climatedata/weath_V.dat
./builelib/climatedata/weath_VI.dat
./builelib/database/AC_gshp_openloop.json
./builelib/database/ACoperationMode.json
./builelib/database/AREA.json
./builelib/database/CALENDAR.json
./builelib/database/EXPS.json
./builelib/database/FLOWCONTROL.json
./builelib/database/HeatSourcePerformance.json
builelib.egg-info/PKG-INFO
builelib.egg-info/SOURCES.txt
builelib.egg-info/dependency_links.txt
builelib.egg-info/top_level.txt