Metadata-Version: 1.2
Name: builelib
Version: 1.1.4
Summary: builelib: Building Energy-modeling Library
Home-page: https://github.com/MasatoMiyata/builelib
Author: Masato Miyata
Author-email: builelib@gmail.com
License: MIT License
